{
	"work": [
		{
      "name": "Write",
      "md": "write",
      "img": "/img/work/write.png"
    },
    {
			"name": "Text Your Rep",
			"md": "text-a-rep",
			"img": "/img/work/rep.png"
		},
		{
			"name": "Slice Capital",
			"md": "slice",
			"img": "/img/work/slice.png"
		},
		{
			"name": "Sitrus Clothing",
			"md": "sitrus",
			"img": "/img/work/sitrus.png"
		},
		{
			"name": "Forward Philly",
			"md": "forward",
			"img": "/img/work/fwd.png"
		},
		{
			"name": "Helix",
			"md": "helix",
			"img": "/img/work/helix.png"
		},
		{
			"name": "goContribute",
			"md": "gocontribute",
			"img": "/img/work/gocontribute.png"
		}
	]
}
